src/__init__.py
src/file_manager.py
src/greetings_cli.py
src/subsys.py
gitinspired_cli-1.0.3.dist-info/LICENSE
gitinspired_cli-1.0.3.dist-info/METADATA
gitinspired_cli-1.0.3.dist-info/WHEEL
gitinspired_cli-1.0.3.dist-info/entry_points.txt
gitinspired_cli-1.0.3.dist-info/top_level.txt
gitinspired_cli-1.0.3.dist-info/RECORD
