Metadata-Version: 2.1
Name: gitinspired-cli
Version: 1.0.3
Summary: UNKNOWN
Home-page: UNKNOWN
Author: UNKNOWN
Author-email: UNKNOWN
License: UNKNOWN
Platform: UNKNOWN
Requires-Dist: argparse
